<?xml version="1.0" encoding="UTF-8"?>
<!DOCTYPE suite SYSTEM "http://testng.org/testng-1.0.dtd">
<suite thread-count="2" name="Suite" parallel="tests">
  <test thread-count="2" name="Test1" parallel="tests">
  <parameter name="browser" value="chrome"/>
    <classes>
      <class name="com.crm.ContactTests.ContactwithLeadsourceOrgLastName"/>
      <class name="com.crm.ContactTests.ContactwithLeadsourceOrgLastName"/>
       </classes>
  </test> <!-- Test -->
  <test thread-count="2" name="Test2" parallel="tests">
  <parameter name="browser" value="firefox"/>
    <classes>
      <class name="com.crm.OraganizationTest.CreateOrgTest"/>
    </classes>
  </test> <!-- Test -->  
</suite> <!-- Suite -->
 